LICENSE
README.md
pyproject.toml
setup.py
Kamyroll_Python.egg-info/PKG-INFO
Kamyroll_Python.egg-info/SOURCES.txt
Kamyroll_Python.egg-info/dependency_links.txt
Kamyroll_Python.egg-info/not-zip-safe
Kamyroll_Python.egg-info/requires.txt
Kamyroll_Python.egg-info/top_level.txt
bin/kamyroll
kamyroll_python/__init__.py
kamyroll_python/api.py
kamyroll_python/converter.py
kamyroll_python/downloader.py
kamyroll_python/extractor.py
kamyroll_python/kamyroll.py
kamyroll_python/utils.py