Metadata-Version: 2.1
Name: Kamyroll-Python
Version: 0.0.2
Summary: Download shows from crunchyroll
Home-page: https://github.com/hyugogirubato/Kamyroll-Python
Author: hyugogirubato
License: MIT
Platform: UNKNOWN
License-File: LICENSE
